Workbook

Sheet INSTRUCCIONES
B2: BTG ETF Genérico · Planilla de Seguimiento Semanal
B3: Guía de uso para el equipo de MKT & Comunicaciones · BTG Pactual Chile
B5: CÓDIGO DE COLORES
C7: Amarillo | E7: Celdas a COMPLETAR por el equipo. Son los campos de ingreso de datos.
C8: Azul claro | E8: Celdas calculadas AUTOMÁTICAMENTE. No editar.
C9: Verde claro | E9: Metas y objetivos del mes. Solo lectura.
C10: Gris azulado | E10: Encabezados de sección. No editar.
B12: CÓMO USAR ESTA PLANILLA
B14: Paso 1 — Inicio de mes | C14: Completar la hoja METAS con el presupuesto y KPIs proyectados para el mes.
B15: Paso 2 — Cada lunes (o viernes) | C15: Completar los datos de la semana anterior en PERFORMANCE, AUDIENCIAS y GA4.
B16: Paso 3 — Agregar nueva fila | C16: Copiar la última fila de datos y pegar debajo. Actualizar semana y período.
B17: Paso 4 — No borrar filas | C17: El historial es importante. Solo agregar, nunca eliminar filas con datos.
B18: Paso 5 — Celdas azules | C18: Son cálculos automáticos. Si modificas datos, estas celdas se actualizan solas.
B20: GLOSARIO DE MÉTRICAS
B22: Métrica | C22: Definición | E22: Métrica | F22: Definición
B23: Impresiones | C23: Nº de veces que el anuncio fue mostrado | E23: Alcance | F23: Nº de personas únicas que vieron el anuncio
B24: Clics | C24: Nº de veces que hicieron clic en el aviso | E24: Sesiones | F24: Visitas al landing page del producto
B25: CPM | C25: Costo por cada 1.000 impresiones | E25: CPC | F25: Costo por cada clic obtenido
B26: CPV | C26: Costo por cada reproducción de video | E26: CPA | F26: Costo por cada acción/conversión lograda
B27: Frecuencia | C27: Promedio de veces que un usuario vio el ad | E27: Registros | F27: Leads capturados directamente en plataforma
B28: Presupuesto | C28: Inversión total ejecutada en el período | E28: Duración media | F28: Tiempo promedio de sesión en el sitio
B29: Views | C29: Reproducciones de video (LinkedIn/Meta) | E29: CTR | F29: Click-Through Rate: Clics / Impresiones
B31: BTG Pactual Chile · MKT & Comunicaciones · Campaña ETF Genérico · Mes 1

Sheet METAS
B2: METAS MENSUALES · BTG ETF Genérico
B4: Completar al inicio de cada mes. Estas metas son referenciadas automáticamente por las hojas GA4 y PERFORMANCE.
B6: Mes | C6: Campaña | D6: Presupuesto Total ($) | E6: Meta Impresiones | F6: Meta Alcance | G6: Meta Sesiones Landing | H6: Meta Frec/ Persona | I6: Meta CPM ($) | J6: Meta CPC ($)
B7: Marzo 2025 | C7: BTG ETF Genérico | D7: 2550000 | E7: 5000000 | F7: 1800000 | G7: 11000 | H7: 2.7

Sheet PERFORMANCE
B2: PERFORMANCE SEMANAL POR PLATAFORMA · BTG ETF Genérico
B4: 🟡 Celdas amarillas = completar 🔵 Celdas azules = calculado automáticamente · Agregar una fila nueva cada semana
B6: IDENTIFICACIÓN | E6: META PLATFORM | L6: LINKEDIN | U6: GOOGLE SEARCH | Y6: TOTALES
B7: Sem. | C7: Período | D7: Resp. | E7: Inversión ($) | F7: Alcance | G7: Impresiones | H7: Clics | I7: Views | J7: CPM ($) | K7: CPC ($) | L7: Inversión ($) | M7: Alcance | N7: Impresiones | O7: Clics | P7: Views | Q7: Registros | R7: CPM ($) | S7: CPC ($) | T7: CPV ($) | U7: Inversión ($) | V7: Impresiones | W7: Clics | X7: CPC ($) | Y7: Inv. Total ($) | Z7: Alcance Total | AA7: Impres. Total | AB7: Clics Total | AC7: CPM Prom ($) | AD7: CPC Prom ($)
B8: S1 | C8: 23-29 Mar | D8: AP | E8: 72628 | F8: 272287 | G8: 337823 | H8: 405 | I8: 199 | J8: 215 | K8: 179 | L8: 151214 | M8: 46474 | N8: 129158 | O8: 109 | P8: 12976 | Q8: 1 | R8: 1171 | S8: 1387 | T8: 12 | U8: 74682 | V8: 2452 | W8: 116 | X8: 644 | Y8: =E8+L8+U8 | Z8: =F8+M8 | AA8: =G8+N8+V8 | AB8: =H8+O8+W8 | AC8: =IF(AA8=0,"-",Y8/AA8*1000) | AD8: =IF(AB8=0,"-",Y8/AB8)
Y9: =E9+L9+U9 | Z9: =F9+M9 | AA9: =G9+N9+V9 | AB9: =H9+O9+W9 | AC9: =IF(AA9=0,"-",Y9/AA9*1000) | AD9: =IF(AB9=0,"-",Y9/AB9)
Y10: =E10+L10+U10 | Z10: =F10+M10 | AA10: =G10+N10+V10 | AB10: =H10+O10+W10 | AC10: =IF(AA10=0,"-",Y10/AA10*1000) | AD10: =IF(AB10=0,"-",Y10/AB10)
Y11: =E11+L11+U11 | Z11: =F11+M11 | AA11: =G11+N11+V11 | AB11: =H11+O11+W11 | AC11: =IF(AA11=0,"-",Y11/AA11*1000) | AD11: =IF(AB11=0,"-",Y11/AB11)
Y12: =E12+L12+U12 | Z12: =F12+M12 | AA12: =G12+N12+V12 | AB12: =H12+O12+W12 | AC12: =IF(AA12=0,"-",Y12/AA12*1000) | AD12: =IF(AB12=0,"-",Y12/AB12)
Y13: =E13+L13+U13 | Z13: =F13+M13 | AA13: =G13+N13+V13 | AB13: =H13+O13+W13 | AC13: =IF(AA13=0,"-",Y13/AA13*1000) | AD13: =IF(AB13=0,"-",Y13/AB13)
Y14: =E14+L14+U14 | Z14: =F14+M14 | AA14: =G14+N14+V14 | AB14: =H14+O14+W14 | AC14: =IF(AA14=0,"-",Y14/AA14*1000) | AD14: =IF(AB14=0,"-",Y14/AB14)
Y15: =E15+L15+U15 | Z15: =F15+M15 | AA15: =G15+N15+V15 | AB15: =H15+O15+W15 | AC15: =IF(AA15=0,"-",Y15/AA15*1000) | AD15: =IF(AB15=0,"-",Y15/AB15)
Y16: =E16+L16+U16 | Z16: =F16+M16 | AA16: =G16+N16+V16 | AB16: =H16+O16+W16 | AC16: =IF(AA16=0,"-",Y16/AA16*1000) | AD16: =IF(AB16=0,"-",Y16/AB16)

Sheet AUDIENCIAS
B2: AUDIENCIAS SEMANAL · BTG ETF Genérico
B4: 🟡 Celdas amarillas = completar · Fuente: LinkedIn Campaign Manager (audiencias LinkedIn) y Meta Ads Manager (audiencias Meta)
B6: ID | D6: BANCA PRIVADA | J6: ALTOS CARGOS | P6: ASSET MANAGEMENT | V6: INVERSIONISTAS RETAIL | AB6: INTERÉS ETF
B7: Sem. | C7: Período | D7: Alcance | E7: Impresiones | F7: CPM ($) | G7: Frecuencia | H7: Usuarios Web | I7: Sesiones Web | J7: Alcance | K7: Impresiones | L7: CPM ($) | M7: Frecuencia | N7: Usuarios Web | O7: Sesiones Web | P7: Alcance | Q7: Impresiones | R7: CPM ($) | S7: Frecuencia | T7: Usuarios Web | U7: Sesiones Web | V7: Alcance | W7: Impresiones | X7: CPM ($) | Y7: Frecuencia | Z7: Usuarios Web | AA7: Sesiones Web | AB7: Alcance | AC7: Impresiones | AD7: CPM ($) | AE7: Frecuencia | AF7: Usuarios Web | AG7: Sesiones Web
B8: S1 | C8: 23-29 Mar | D8: 13801 | E8: 35964 | F8: 2048 | G8: 2.6 | H8: 233 | I8: 244 | J8: 25718 | K8: 58405 | L8: 676 | M8: 2.2 | N8: 163 | O8: 177 | P8: 12088 | Q8: 34779 | R8: 1034 | S8: 2.8 | T8: 163 | U8: 171 | V8: 257456 | W8: 313311 | X8: 214 | Y8: 1.2 | Z8: 187 | AA8: 187 | AB8: 21697 | AC8: 24512 | AD8: 222 | AE8: 1.1 | AF8: 17 | AG8: 17

Sheet GA4
B2: GA4 & ANALYTICS SEMANAL · BTG ETF Genérico
B4: 🟡 Celdas amarillas = completar 🔵 Celdas azules = % calculado vs metas (referencia hoja METAS) · Fuente: Google Analytics 4
B6: IDENTIFICACIÓN | D6: ACUMULADO DEL MES | J6: LANDING TOTAL (semana) | M6: BOTÓN FONDO (semana)
B7: Sem. | C7: Período | D7: Impresiones Acum. | E7: Alcance Acum. | F7: Sesiones ETF Acum. | G7: % Avance Impresiones | H7: % Avance Alcance | I7: % Avance Sesiones | J7: Usuarios | K7: Sesiones | L7: Duración Media | M7: Usuarios | N7: Sesiones | O7: Duración Media
B8: S1 | C8: 23-29 Mar | D8: 640356 | E8: 369761 | F8: 2160 | G8: =IF(METAS!D7=0,"-",D8/METAS!D7) | H8: =IF(METAS!E7=0,"-",E8/METAS!E7) | I8: =IF(METAS!F7=0,"-",F8/METAS!F7) | J8: 483 | K8: 524 | L8: 10:00 | M8: 40 | N8: 43 | O8: 09:46
G9: =IF(METAS!D7=0,"-",D9/METAS!D7) | H9: =IF(METAS!E7=0,"-",E9/METAS!E7) | I9: =IF(METAS!F7=0,"-",F9/METAS!F7)
G10: =IF(METAS!D7=0,"-",D10/METAS!D7) | H10: =IF(METAS!E7=0,"-",E10/METAS!E7) | I10: =IF(METAS!F7=0,"-",F10/METAS!F7)
G11: =IF(METAS!D7=0,"-",D11/METAS!D7) | H11: =IF(METAS!E7=0,"-",E11/METAS!E7) | I11: =IF(METAS!F7=0,"-",F11/METAS!F7)
G12: =IF(METAS!D7=0,"-",D12/METAS!D7) | H12: =IF(METAS!E7=0,"-",E12/METAS!E7) | I12: =IF(METAS!F7=0,"-",F12/METAS!F7)
G13: =IF(METAS!D7=0,"-",D13/METAS!D7) | H13: =IF(METAS!E7=0,"-",E13/METAS!E7) | I13: =IF(METAS!F7=0,"-",F13/METAS!F7)
G14: =IF(METAS!D7=0,"-",D14/METAS!D7) | H14: =IF(METAS!E7=0,"-",E14/METAS!E7) | I14: =IF(METAS!F7=0,"-",F14/METAS!F7)
G15: =IF(METAS!D7=0,"-",D15/METAS!D7) | H15: =IF(METAS!E7=0,"-",E15/METAS!E7) | I15: =IF(METAS!F7=0,"-",F15/METAS!F7)
G16: =IF(METAS!D7=0,"-",D16/METAS!D7) | H16: =IF(METAS!E7=0,"-",E16/METAS!E7) | I16: =IF(METAS!F7=0,"-",F16/METAS!F7)
